openfisca_tunisia/__init__.py
openfisca_tunisia/conv.py
openfisca_tunisia/entities.py
openfisca_tunisia/scenarios.py
openfisca_tunisia/tunisia_taxbenefitsystem.py
openfisca_tunisia/units.yaml
openfisca_tunisia/assets/lang/ar.json
openfisca_tunisia/notebooks/demo.ipynb
openfisca_tunisia/notebooks/test_notebooks.py
openfisca_tunisia/parameters/energie/index.yaml
openfisca_tunisia/parameters/energie/gaz/index.yaml
openfisca_tunisia/parameters/energie/gaz/prix.yaml
openfisca_tunisia/parameters/impot_revenu/bareme.yaml
openfisca_tunisia/parameters/impot_revenu/contribution_budget_etat.yaml
openfisca_tunisia/parameters/impot_revenu/index.yaml
openfisca_tunisia/parameters/impot_revenu/bic/index.yaml
openfisca_tunisia/parameters/impot_revenu/bic/forf/acc.yaml
openfisca_tunisia/parameters/impot_revenu/bic/forf/bareme.yaml
openfisca_tunisia/parameters/impot_revenu/bic/forf/forfait.yaml
openfisca_tunisia/parameters/impot_revenu/bic/forf/index.yaml
openfisca_tunisia/parameters/impot_revenu/bic/reel/forfait.yaml
openfisca_tunisia/parameters/impot_revenu/bic/reel/index.yaml
openfisca_tunisia/parameters/impot_revenu/bic/simpl/forfait.yaml
openfisca_tunisia/parameters/impot_revenu/bic/simpl/index.yaml
openfisca_tunisia/parameters/impot_revenu/bnc/index.yaml
openfisca_tunisia/parameters/impot_revenu/bnc/forf/index.yaml
openfisca_tunisia/parameters/impot_revenu/bnc/forf/part_forf.yaml
openfisca_tunisia/parameters/impot_revenu/deductions/index.yaml
openfisca_tunisia/parameters/impot_revenu/deductions/assurance_vie/conj_plaf.yaml
openfisca_tunisia/parameters/impot_revenu/deductions/assurance_vie/enf_plaf.yaml
openfisca_tunisia/parameters/impot_revenu/deductions/assurance_vie/index.yaml
openfisca_tunisia/parameters/impot_revenu/deductions/assurance_vie/plaf.yaml
openfisca_tunisia/parameters/impot_revenu/deductions/banq/index.yaml
openfisca_tunisia/parameters/impot_revenu/deductions/banq/plaf.yaml
openfisca_tunisia/parameters/impot_revenu/deductions/cent/index.yaml
openfisca_tunisia-0.56.dist-info/licenses/LICENSE.AGPL.txt
openfisca_tunisia-0.56.dist-info/METADATA
openfisca_tunisia-0.56.dist-info/WHEEL
openfisca_tunisia-0.56.dist-info/top_level.txt
openfisca_tunisia-0.56.dist-info/RECORD
