Metadata-Version: 2.4
Name: OpenFisca-Tunisia
Version: 0.56
Summary: OpenFisca Rules as Code model for Tunisia.
Author-email: OpenFisca Team <contact@openfisca.org>
Project-URL: Homepage, https://github.com/openfisca/openfisca-tunisia
Project-URL: Repository, https://github.com/openfisca/openfisca-tunisia
Project-URL: Documentation, https://openfisca.org/doc
Project-URL: Issues, https://github.com/openfisca/openfisca-tunisia/issues
Project-URL: Changelog, https://github.com/openfisca/openfisca-tunisia/blob/main/CHANGELOG.md
Keywords: microsimulation,tax,benefit,rac,rules-as-code,tunisia
Classifier: Development Status :: 5 - Production/Stable
Classifier: License :: OSI Approved :: GNU Affero General Public License v3
Classifier: Operating System :: POSIX
Classifier: Programming Language :: Python
Classifier: Programming Language :: Python :: 3.9
Classifier: Programming Language :: Python :: 3.10
Classifier: Programming Language :: Python :: 3.11
Classifier: Topic :: Scientific/Engineering :: Information Analysis
Requires-Python: >=3.9
License-File: LICENSE.AGPL.txt
Requires-Dist: numpy<2,>=1.24.3
Requires-Dist: openfisca-core[web-api]<44,>=43
Provides-Extra: dev
Requires-Dist: autopep8<3.0,>=2.0.2; extra == "dev"
Requires-Dist: Flake8-pyproject<2.0.0,>=1.2.3; extra == "dev"
Requires-Dist: flake8<7.0.0,>=6.0.0; extra == "dev"
Requires-Dist: flake8-print<6.0.0,>=5.0.0; extra == "dev"
Requires-Dist: flake8-quotes>=3.3.2; extra == "dev"
Requires-Dist: pytest; extra == "dev"
Requires-Dist: scipy<2.0,>=1.10.1; extra == "dev"
Requires-Dist: requests<3.0,>=2.28.2; extra == "dev"
Requires-Dist: yamllint<2.0,>=1.30.0; extra == "dev"
Provides-Extra: notebook
Requires-Dist: ipykernel>=4.8; extra == "notebook"
Requires-Dist: jupyter-client>=5.2; extra == "notebook"
Requires-Dist: matplotlib>=2.2; extra == "notebook"
Requires-Dist: nbconvert>=5.3; extra == "notebook"
Requires-Dist: nbformat>=4.4; extra == "notebook"
Requires-Dist: pandas>=0.22.0; extra == "notebook"
Dynamic: license-file
